langtable/__init__.py
langtable/langtable.py
langtable/data/keyboards.xml.gz
langtable/data/languages.xml.gz
langtable/data/territories.xml.gz
langtable/data/timezoneidparts.xml.gz
langtable/data/timezones.xml.gz
langtable/schemas/keyboards.rng
langtable/schemas/languages.rng
langtable/schemas/territories.rng
langtable/schemas/timezoneidparts.rng
langtable/schemas/timezones.rng
langtable-0.0.69.dist-info/licenses/COPYING
langtable-0.0.69.dist-info/METADATA
langtable-0.0.69.dist-info/WHEEL
langtable-0.0.69.dist-info/top_level.txt
langtable-0.0.69.dist-info/RECORD
