Metadata-Version: 2.4
Name: langtable
Version: 0.0.69
Summary: guess reasonable defaults for locale, keyboard, territory, ...
Home-page: https://github.com/mike-fabian/langtable
Author: Mike FABIAN
Author-email: mfabian@redhat.com
License: GPL-3.0-or-later
Classifier: Development Status :: 2 - Pre-Alpha
Classifier: Environment :: Console
Classifier: Intended Audience :: Developers
Classifier: Operating System :: POSIX :: Linux
Classifier: Programming Language :: Python
Classifier: Topic :: System :: Installation/Setup
License-File: COPYING
Dynamic: author
Dynamic: author-email
Dynamic: classifier
Dynamic: description
Dynamic: description-content-type
Dynamic: home-page
Dynamic: license
Dynamic: license-file
Dynamic: summary
